{
  "lessonId": "hsk4_gate_16",
  "level": "HSK4",
  "gateId": 16,
  "title": "HSK4 Gate 16 Lesson",
  "explanation": "HSK4 Gate 16：本关有 14 个生字和 24 个复习字。先认读下面的词，再读短文，最后做理解题。大部分内容你可以自己完成；不懂的地方可以问家长（约二成时间）。",
  "passage": "第16关：今天的新词有：出色、冰、结、材料、转移、烦、付出、卷、透、治……等（共14个生字）。复习字有：躺、采访、针对、即将、宝、答案、规则、激动……等（共24个）。请你先听一听（或请家长读一遍），再自己大声读两遍。然后试着用本关的一个新词说一句很短的中文。",
  "keyVocab": [
    {
      "zh": "出色",
      "pinyin": "chū sè",
      "en": "remarkable; outstanding"
    },
    {
      "zh": "冰",
      "pinyin": "bīng",
      "en": "ice"
    },
    {
      "zh": "结",
      "pinyin": "jiē",
      "en": "(of a plant) to produce (fruit or seeds)"
    },
    {
      "zh": "材料",
      "pinyin": "cái liào",
      "en": "(raw) material"
    },
    {
      "zh": "转移",
      "pinyin": "zhuǎn yí",
      "en": "to shift; to relocate; to transfer"
    },
    {
      "zh": "烦",
      "pinyin": "fán",
      "en": "to feel vexed"
    },
    {
      "zh": "付出",
      "pinyin": "fù chū",
      "en": "to pay; to expend; to invest (energy or time)"
    },
    {
      "zh": "卷",
      "pinyin": "juǎn",
      "en": "to roll up"
    },
    {
      "zh": "透",
      "pinyin": "tòu",
      "en": "(bound form) to penetrate; to seep through"
    },
    {
      "zh": "治",
      "pinyin": "zhì",
      "en": "to rule"
    },
    {
      "zh": "措施",
      "pinyin": "cuò shī",
      "en": "measure"
    },
    {
      "zh": "失望",
      "pinyin": "shī wàng",
      "en": "disappointed"
    },
    {
      "zh": "号码",
      "pinyin": "hào mǎ",
      "en": "number"
    },
    {
      "zh": "利益",
      "pinyin": "lì yì",
      "en": "benefit"
    }
  ],
  "comprehension": [
    {
      "question": "本关有几个生字（新词）？",
      "answer": "14个。"
    },
    {
      "question": "请说出两个“复习字”（从短文里的复习列表选）。",
      "answer": "例如：躺 和 采访（答案不唯一，合理即可）。"
    },
    {
      "question": "读完以后，你应该自己先做哪一步？",
      "answer": "大声读词和短文，再用新词说一句短句（需要时请家长帮忙）。"
    }
  ],
  "speakingPrompt": "用本关的词（例如「出色」「冰」）说 2～3 句很短的中文，可以说你的一天或你的爱好。"
}
